{
	"schemaVersion": 1,
	"id": "pmc",
	"version": "${version}",
	"name": "PMC",
	"description": "Allows servers to interact with the client more than Vanilla should ever allow",
	"authors": [
		"RooXChicken"
	],
	"contact": {
		"homepage": "https://fabricmc.net/",
		"sources": "https://github.com/FabricMC/fabric-example-mod"
	},
	"license": "CC0-1.0",
	"icon": "assets/pmc/icon.png",
	"environment": "*",
	"entrypoints": {
		"main": [ "com.rooxchicken.pmc.PMC" ],
		"client": [ "com.rooxchicken.pmc.PMCClient" ]
	},
	"mixins": [
		"pmc.mixins.json"
	],
	"depends": {
		"fabricloader": ">=0.15.2",
		"minecraft": "~1.21",
		"java": ">=21",
		"fabric-api": "*"
	},
	"suggests": {
		"another-mod": "*"
	}
}
